ksddescent/__init__.py
ksddescent/contenders.py
ksddescent/kernels.py
ksddescent/ksd_descent.py
ksddescent-0.3.dist-info/LICENSE
ksddescent-0.3.dist-info/METADATA
ksddescent-0.3.dist-info/WHEEL
ksddescent-0.3.dist-info/top_level.txt
ksddescent-0.3.dist-info/RECORD
