Metadata-Version: 2.1
Name: ksddescent
Version: 0.3
Summary: Kernel Stein Discrepancy descent
Home-page: UNKNOWN
Maintainer: XXX XXX
Maintainer-email: xxx@xxx.com
License: BSD (3-clause)
Download-URL: https://github.com/XXX/XXX.git
Platform: any
Classifier: Intended Audience :: Science/Research
Classifier: Intended Audience :: Developers
Classifier: License :: OSI Approved
Classifier: Programming Language :: Python
Classifier: Topic :: Software Development
Classifier: Topic :: Scientific/Engineering
Classifier: Operating System :: Microsoft :: Windows
Classifier: Operating System :: POSIX
Classifier: Operating System :: Unix
Classifier: Operating System :: MacOS
License-File: LICENSE
Requires-Dist: numpy (>=1.15)
Requires-Dist: scipy
Requires-Dist: torch (>=1.7)
